compute/__init__.py
compute/client.py
compute/execution.py
compute/factory.py
compute/graph.py
compute/queries.py
compute/storage.py
compute/types.py
compute/utils.py
enterprise_platform_compute-0.0.4.dist-info/METADATA
enterprise_platform_compute-0.0.4.dist-info/WHEEL
enterprise_platform_compute-0.0.4.dist-info/top_level.txt
enterprise_platform_compute-0.0.4.dist-info/RECORD
