Metadata-Version: 2.1
Name: enterprise-platform-compute
Version: 0.0.4
Summary: UNKNOWN
Home-page: UNKNOWN
License: UNKNOWN
Platform: UNKNOWN
Requires-Dist: cloudpickle (==2.2.1)
Requires-Dist: gql[botocore,requests] (==3.4.0)
Requires-Dist: httpx (==0.24.0)
Requires-Dist: networkx (==3.1)
Requires-Dist: polling2 (==0.5.0)
Requires-Dist: rich (==13.3.5)
Requires-Dist: websockets (==11.0.2)
